pgsu/__init__.py
pgsu/cli.py
pgsu-0.3.0.dist-info/entry_points.txt
pgsu-0.3.0.dist-info/LICENSE
pgsu-0.3.0.dist-info/WHEEL
pgsu-0.3.0.dist-info/METADATA
pgsu-0.3.0.dist-info/RECORD
