Metadata-Version: 2.1
Name: pgsu
Version: 0.3.0
Summary: Connect to an existing PostgreSQL cluster as the `postgres` superuser and execute SQL commands.
Author-email: AiiDA Team <aiidateam@gmail.com>
Requires-Python: >=3.7
Classifier: License :: OSI Approved :: MIT License
Classifier: Operating System :: MacOS :: MacOS X
Classifier: Operating System :: Microsoft :: Windows
Classifier: Operating System :: POSIX :: Linux
Classifier: Programming Language :: Python
Classifier: Programming Language :: Python :: 3
Classifier: Programming Language :: Python :: 3 :: Only
Classifier: Programming Language :: Python :: 3.7
Classifier: Programming Language :: Python :: 3.8
Classifier: Programming Language :: Python :: 3.9
Classifier: Programming Language :: Python :: 3.10
Classifier: Programming Language :: Python :: 3.11
Classifier: Programming Language :: Python :: Implementation :: CPython
Requires-Dist: click
Requires-Dist: psycopg[binary]>=3.0
Requires-Dist: pre-commit~=2.2 ; extra == "dev"
Requires-Dist: pylint~=2.5.0 ; extra == "dev"
Requires-Dist: pgtest>=1.3.1 ; extra == "dev"
Requires-Dist: pytest ; extra == "dev"
Requires-Dist: pytest-cov ; extra == "dev"
Project-URL: homepage, https://github.com/aiidateam/pgsu
Project-URL: source, https://github.com/aiidateam/pgsu
Project-URL: tracker, https://github.com/aiidateam/pgsu/issues
Provides-Extra: dev
